tg_webm_converter/__init__.py
tg_webm_converter/cli.py
tg_webm_converter/converter.py
tg_webm_converter/runner.py
tg_webm_converter-0.1.1.dist-info/LICENSE
tg_webm_converter-0.1.1.dist-info/METADATA
tg_webm_converter-0.1.1.dist-info/WHEEL
tg_webm_converter-0.1.1.dist-info/entry_points.txt
tg_webm_converter-0.1.1.dist-info/RECORD
