Metadata-Version: 2.3
Name: tg-webm-converter
Version: 0.1.1
Summary: Convert images to Telegram WebM stickers.
License: MIT
Keywords: webm,sticker,icon,conversion,ffmpeg
Author: Yeongjin Kim
Author-email: 77034308+7591yj@users.noreply.github.com
Requires-Python: >=3.12,<4.0
Classifier: Development Status :: 4 - Beta
Classifier: Intended Audience :: Developers
Classifier: Intended Audience :: End Users/Desktop
Classifier: License :: OSI Approved :: MIT License
Classifier: Operating System :: OS Independent
Classifier: Programming Language :: Python :: 3
Classifier: Programming Language :: Python :: 3.12
Classifier: Programming Language :: Python :: 3.13
Classifier: Programming Language :: Python :: 3.10
Classifier: Programming Language :: Python :: 3.11
Classifier: Programming Language :: Python :: 3.8
Classifier: Programming Language :: Python :: 3.9
Classifier: Topic :: Multimedia :: Graphics :: Graphics Conversion
Requires-Dist: click (>=8.1.7,<9.0.0)
Project-URL: Homepage, https://github.com/7591yj/tg-webm-converter
Project-URL: Repository, https://github.com/7591yj/tg-webm-converter
